silero_vad/__init__.py
silero_vad/model.py
silero_vad/utils_vad.py
silero_vad/data/__init__.py
silero_vad/data/silero_vad.jit
silero_vad/data/silero_vad.onnx
silero_vad/data/silero_vad_16k_op15.onnx
silero_vad/data/silero_vad_half.onnx
silero_vad-6.1.0.dist-info/METADATA
silero_vad-6.1.0.dist-info/WHEEL
silero_vad-6.1.0.dist-info/licenses/LICENSE
silero_vad-6.1.0.dist-info/RECORD
