Metadata-Version: 2.4
Name: silero-vad
Version: 6.1.0
Summary: Voice Activity Detector (VAD) by Silero
Project-URL: Homepage, https://github.com/snakers4/silero-vad
Project-URL: Issues, https://github.com/snakers4/silero-vad/issues
Author-email: Silero Team <hello@silero.ai>
License-File: LICENSE
Classifier: Development Status :: 5 - Production/Stable
Classifier: Intended Audience :: Developers
Classifier: Intended Audience :: Science/Research
Classifier: License :: OSI Approved :: MIT License
Classifier: Operating System :: OS Independent
Classifier: Programming Language :: Python :: 3.8
Classifier: Programming Language :: Python :: 3.9
Classifier: Programming Language :: Python :: 3.10
Classifier: Programming Language :: Python :: 3.11
Classifier: Programming Language :: Python :: 3.12
Classifier: Programming Language :: Python :: 3.13
Classifier: Programming Language :: Python :: 3.14
Classifier: Programming Language :: Python :: 3.15
Classifier: Topic :: Scientific/Engineering
Classifier: Topic :: Scientific/Engineering :: Artificial Intelligence
Requires-Python: >=3.8
Requires-Dist: onnxruntime>=1.16.1
Requires-Dist: packaging
Requires-Dist: torch>=1.12.0
Requires-Dist: torchaudio>=0.12.0
